MANIFEST.in
setup.cfg
setup.py
anankeesol/__init__.py
anankeesol/ananke_details.txt
anankeesol/anankeesol.py
anankeesol.egg-info/PKG-INFO
anankeesol.egg-info/SOURCES.txt
anankeesol.egg-info/dependency_links.txt
anankeesol.egg-info/not-zip-safe
anankeesol.egg-info/requires.txt
anankeesol.egg-info/top_level.txt