Metadata-Version: 1.0
Name: anankeesol
Version: 1.0.0
Summary: This sdk is used to connect Ananke IOT platform
Home-page: UNKNOWN
Author: Effective Solutions LtD Sri Lanka
Author-email: bathiyathennakoon@gmail.com
License: MIT
Platform: UNKNOWN
